Metadata-Version: 2.1
Name: robotframework-debug-dk
Version: 1.0.0
Summary: RobotFramework debug shell originally implemented by René Rohner and modified by Maciej Banakiewicz
Home-page: https://github.com/maciejbanakiewicz93/robotframework-debug/
Author: René Rohner (modified by Maciej Banakiewicz)
Author-email: snooz@postoe.de
License: New BSD
Keywords: robotframework,debug,shell,repl
Platform: Linux
Platform: Unix
Platform: Windows
Platform: MacOS X
Classifier: Environment :: Console
Classifier: Development Status :: 5 - Production/Stable
Classifier: License :: OSI Approved :: BSD License
Classifier: Natural Language :: English
Classifier: Operating System :: OS Independent
Classifier: Programming Language :: Python
Classifier: Programming Language :: Python :: 3 :: Only
Classifier: Programming Language :: Python :: 3.7
Classifier: Programming Language :: Python :: 3.8
Classifier: Programming Language :: Python :: 3.9
Classifier: Programming Language :: Python :: 3.10
Classifier: Topic :: Utilities
Requires-Python: >=3.8.0
License-File: LICENSE
Requires-Dist: prompt-toolkit >=3.0.38
Requires-Dist: robotframework >=5.0
Requires-Dist: pygments >=2.14.0
Requires-Dist: pyperclip >=1.8.2
